{
  "id": "a3620c7b-b6fe-40be-9970-e306e8112026",
  "prevId": "8fd26131-6f82-4cf9-a12d-2886868b0a57",
  "version": "7",
  "dialect": "postgresql",
  "tables": {
    "public.customerdata": {
      "name": "customerdata",
      "schema": "",
      "columns": {
        "id": {
          "name": "id",
          "type": "serial",
          "primaryKey": true,
          "notNull": true
        },
        "customer_name": {
          "name": "customer_name",
          "type": "varchar",
          "primaryKey": false,
          "notNull": false
        },
        "phone_number": {
          "name": "phone_number",
          "type": "varchar",
          "primaryKey": false,
          "notNull": false
        },
        "customer_order": {
          "name": "customer_order",
          "type": "text[]",
          "primaryKey": false,
          "notNull": true
        },
        "total_price": {
          "name": "total_price",
          "type": "varchar",
          "primaryKey": false,
          "notNull": true
        }
      },
      "indexes": {},
      "foreignKeys": {},
      "compositePrimaryKeys": {},
      "uniqueConstraints": {},
      "policies": {},
      "checkConstraints": {},
      "isRLSEnabled": false
    },
    "public.drinks": {
      "name": "drinks",
      "schema": "",
      "columns": {
        "id": {
          "name": "id",
          "type": "serial",
          "primaryKey": true,
          "notNull": true
        },
        "image_url": {
          "name": "image_url",
          "type": "varchar",
          "primaryKey": false,
          "notNull": true
        },
        "drinks_name": {
          "name": "drinks_name",
          "type": "varchar",
          "primaryKey": false,
          "notNull": true
        },
        "510ml_price": {
          "name": "510ml_price",
          "type": "varchar",
          "primaryKey": false,
          "notNull": true
        },
        "2l_price": {
          "name": "2l_price",
          "type": "varchar",
          "primaryKey": false,
          "notNull": true
        }
      },
      "indexes": {},
      "foreignKeys": {},
      "compositePrimaryKeys": {},
      "uniqueConstraints": {},
      "policies": {},
      "checkConstraints": {},
      "isRLSEnabled": false
    },
    "public.pizza": {
      "name": "pizza",
      "schema": "",
      "columns": {
        "id": {
          "name": "id",
          "type": "serial",
          "primaryKey": true,
          "notNull": true
        },
        "name": {
          "name": "name",
          "type": "varchar(255)",
          "primaryKey": false,
          "notNull": true
        },
        "image_url": {
          "name": "image_url",
          "type": "varchar",
          "primaryKey": false,
          "notNull": true
        },
        "price_small": {
          "name": "price_small",
          "type": "varchar",
          "primaryKey": false,
          "notNull": true
        },
        "price_medium": {
          "name": "price_medium",
          "type": "varchar",
          "primaryKey": false,
          "notNull": true
        },
        "price_large": {
          "name": "price_large",
          "type": "varchar",
          "primaryKey": false,
          "notNull": true
        }
      },
      "indexes": {},
      "foreignKeys": {},
      "compositePrimaryKeys": {},
      "uniqueConstraints": {},
      "policies": {},
      "checkConstraints": {},
      "isRLSEnabled": false
    },
    "public.sides": {
      "name": "sides",
      "schema": "",
      "columns": {
        "id": {
          "name": "id",
          "type": "serial",
          "primaryKey": true,
          "notNull": true
        },
        "item_name": {
          "name": "item_name",
          "type": "varchar",
          "primaryKey": false,
          "notNull": true
        },
        "image_url": {
          "name": "image_url",
          "type": "varchar",
          "primaryKey": false,
          "notNull": true
        },
        "small_price": {
          "name": "small_price",
          "type": "varchar",
          "primaryKey": false,
          "notNull": false
        },
        "regular_price": {
          "name": "regular_price",
          "type": "varchar",
          "primaryKey": false,
          "notNull": false
        },
        "large_price": {
          "name": "large_price",
          "type": "varchar",
          "primaryKey": false,
          "notNull": false
        }
      },
      "indexes": {},
      "foreignKeys": {},
      "compositePrimaryKeys": {},
      "uniqueConstraints": {},
      "policies": {},
      "checkConstraints": {},
      "isRLSEnabled": false
    },
    "public.users": {
      "name": "users",
      "schema": "",
      "columns": {
        "id": {
          "name": "id",
          "type": "serial",
          "primaryKey": true,
          "notNull": true
        },
        "userName": {
          "name": "userName",
          "type": "varchar",
          "primaryKey": false,
          "notNull": true
        },
        "password": {
          "name": "password",
          "type": "varchar(255)",
          "primaryKey": false,
          "notNull": true
        },
        "createdAt": {
          "name": "createdAt",
          "type": "timestamp",
          "primaryKey": false,
          "notNull": false,
          "default": "now()"
        }
      },
      "indexes": {},
      "foreignKeys": {},
      "compositePrimaryKeys": {},
      "uniqueConstraints": {
        "users_userName_unique": {
          "name": "users_userName_unique",
          "nullsNotDistinct": false,
          "columns": [
            "userName"
          ]
        }
      },
      "policies": {},
      "checkConstraints": {},
      "isRLSEnabled": false
    }
  },
  "enums": {},
  "schemas": {},
  "sequences": {},
  "roles": {},
  "policies": {},
  "views": {},
  "_meta": {
    "columns": {},
    "schemas": {},
    "tables": {}
  }
}